fixup/__init__.py
fixup/_find_unused_imports.py
fixup-0.0.0.dist-info/entry_points.txt
fixup-0.0.0.dist-info/LICENSE
fixup-0.0.0.dist-info/WHEEL
fixup-0.0.0.dist-info/METADATA
fixup-0.0.0.dist-info/RECORD
