Metadata-Version: 2.1
Name: fixup
Version: 0.0.0
Summary: Automatically add and remove python import statements
Author: Jasha Sommer-Simpson
Classifier: License :: OSI Approved :: MIT License
Requires-Dist: libcst
Requires-Dist: pytest >=2.7.3 ; extra == "test"
Requires-Dist: pylint ; extra == "test"
Requires-Dist: pyflakes ; extra == "test"
Requires-Dist: mypy ; extra == "test"
Requires-Dist: pyright ; extra == "test"
Requires-Dist: black ; extra == "test"
Requires-Dist: isort ; extra == "test"
Provides-Extra: test
